binance/__init__.py
binance/client.py
binance/definitions.py
binance/errors.py
binance/events.py
binance/http.py
binance/web_sockets.py
binance.py-1.9.0.dist-info/LICENSE.md
binance.py-1.9.0.dist-info/METADATA
binance.py-1.9.0.dist-info/WHEEL
binance.py-1.9.0.dist-info/top_level.txt
binance.py-1.9.0.dist-info/RECORD
