Metadata-Version: 2.1
Name: binance.py
Version: 1.9.0
Summary: A python3 binance API wrapper powered by modern technologies such as asyncio
Home-page: https://git.io/binance.py
Author: Th0rgal
Author-email: thomas.marchand@tuta.io
License: UNKNOWN
Platform: UNKNOWN
Classifier: Programming Language :: Python :: 3
Classifier: License :: OSI Approved :: MIT License
Classifier: Operating System :: OS Independent
Requires-Python: >=3.6
Requires-Dist: aiohttp (>=3.6.3)
